README.rst
setup.py
django_modelsubscription.egg-info/PKG-INFO
django_modelsubscription.egg-info/SOURCES.txt
django_modelsubscription.egg-info/dependency_links.txt
django_modelsubscription.egg-info/requires.txt
django_modelsubscription.egg-info/top_level.txt
modelsubscription/__init__.py
modelsubscription/models.py
modelsubscription/settings.py
modelsubscription/handlers/__init__.py
modelsubscription/handlers/dbhandler.py
modelsubscription/handlers/emailhandler.py
modelsubscription/handlers/subscriptionhandlerbase.py
testing/__init__.py
testing/models.py
testing/settings.py
testing/tests.py
testing/urls.py