Metadata-Version: 1.1
Name: django-modelsubscription
Version: 0.0.1
Summary: Generic model mixin for user or email subscription to objects
Home-page: https://github.com/kaleidos/django-modelsubscription
Author: Jesús Espino García
Author-email: jespinog@gmail.com
License: BSD
Keywords: django,model
Platform: UNKNOWN
Classifier: Programming Language :: Python
Classifier: Development Status :: 4 - Beta
Classifier: Framework :: Django
Classifier: Intended Audience :: Developers
Classifier: License :: OSI Approved :: BSD License
Classifier: Operating System :: OS Independent
Classifier: Programming Language :: Python
Classifier: Topic :: Internet :: WWW/HTTP
